AUTHORS.rst
CONTRIBUTING.rst
HISTORY.rst
LICENSE
MANIFEST.in
README.rst
setup.cfg
setup.py
docs/Makefile
docs/authors.rst
docs/conf.py
docs/contributing.rst
docs/history.rst
docs/index.rst
docs/installation.rst
docs/make.bat
docs/readme.rst
docs/usage.rst
griddypower/__init__.py
griddypower/async_api.py
griddypower.egg-info/PKG-INFO
griddypower.egg-info/SOURCES.txt
griddypower.egg-info/dependency_links.txt
griddypower.egg-info/not-zip-safe
griddypower.egg-info/requires.txt
griddypower.egg-info/top_level.txt
tests/__init__.py
tests/test_async_api.py
tests/fixtures/getnow.json