Metadata-Version: 1.2
Name: griddypower
Version: 0.1.0
Summary: Python API for Griddy Wholesale Electricity
Home-page: https://github.com/bdraco/griddypower
Author: J. Nick Koston
Author-email: nick@koston.org
License: BSD license
Keywords: griddypower
Platform: UNKNOWN
Classifier: Development Status :: 2 - Pre-Alpha
Classifier: Intended Audience :: Developers
Classifier: License :: OSI Approved :: BSD License
Classifier: Natural Language :: English
Classifier: Programming Language :: Python :: 3
Classifier: Programming Language :: Python :: 3.5
Classifier: Programming Language :: Python :: 3.6
Classifier: Programming Language :: Python :: 3.7
Classifier: Programming Language :: Python :: 3.8
Requires-Python: >=3.5
